fractal_healthcheck/__init__.py
fractal_healthcheck/main.py
fractal_healthcheck/report.py
fractal_healthcheck/checks/CheckResults.py
fractal_healthcheck/checks/__init__.py
fractal_healthcheck/checks/implementations.py
fractal_healthcheck-0.1.17.dist-info/licenses/LICENSE
fractal_healthcheck-0.1.17.dist-info/METADATA
fractal_healthcheck-0.1.17.dist-info/WHEEL
fractal_healthcheck-0.1.17.dist-info/entry_points.txt
fractal_healthcheck-0.1.17.dist-info/top_level.txt
fractal_healthcheck-0.1.17.dist-info/RECORD
