Metadata-Version: 2.4
Name: fractal-healthcheck
Version: 0.1.17
Summary: A simple tool to monitor Fractal instances
Author-email: Alberto Pastorutti <alberto.pastorutti@exact-lab.it>, Tommaso Comparin <tommaso.comparin@exact-lab.it>
License: BSD 3-Clause License
Requires-Python: >=3.10
License-File: LICENSE
Requires-Dist: click<8.2.0,>=8.1.0
Requires-Dist: psutil<7.2.0,>=7.1.0
Requires-Dist: pyyaml<6.1.0,>=6.0.0
Requires-Dist: pydantic[email]<2.11.0,>=2.10.0
Requires-Dist: urllib3<3.0.0,>=2.3.0
Requires-Dist: paramiko<4.1.0,>=4.0.0
Requires-Dist: fabric<4.0.0,>=3.2.2
Requires-Dist: psycopg[binary]<4.0.0,>=3.2.9
Provides-Extra: dev
Requires-Dist: bumpver; extra == "dev"
Requires-Dist: devtools>=0.12.2; extra == "dev"
Requires-Dist: pytest<9.0.0,>=8.3.0; extra == "dev"
Requires-Dist: pre-commit>=2.19; extra == "dev"
Requires-Dist: requests<3.0.0,>=2.32.0; extra == "dev"
Dynamic: license-file
